wink_sdk_extranet_property/__init__.py
wink_sdk_extranet_property/api_client.py
wink_sdk_extranet_property/api_response.py
wink_sdk_extranet_property/configuration.py
wink_sdk_extranet_property/exceptions.py
wink_sdk_extranet_property/py.typed
wink_sdk_extranet_property/rest.py
wink_sdk_extranet_property/api/__init__.py
wink_sdk_extranet_property/api/announcement_api.py
wink_sdk_extranet_property/api/channel_manager_api.py
wink_sdk_extranet_property/api/geo_location_api.py
wink_sdk_extranet_property/api/lifestyle_api.py
wink_sdk_extranet_property/api/media_api.py
wink_sdk_extranet_property/api/policy_api.py
wink_sdk_extranet_property/api/property_api.py
wink_sdk_extranet_property/api/recognition_api.py
wink_sdk_extranet_property/api/reference_api.py
wink_sdk_extranet_property/api/social_network_api.py
wink_sdk_extranet_property/models/__init__.py
wink_sdk_extranet_property/models/address_supplier.py
wink_sdk_extranet_property/models/aggregate_descriptor_supplier.py
wink_sdk_extranet_property/models/aggregate_greendex_answers_supplier.py
wink_sdk_extranet_property/models/aggregate_greendex_score_by_category_supplier.py
wink_sdk_extranet_property/models/announcement_supplier.py
wink_sdk_extranet_property/models/announcement_view_supplier.py
wink_sdk_extranet_property/models/change_property_name_request_supplier.py
wink_sdk_extranet_property/models/composite_filter_descriptor_supplier.py
wink_sdk_extranet_property/models/contact_supplier.py
wink_sdk_extranet_property/models/country_lightweight_supplier.py
wink_sdk_extranet_property/models/country_supplier.py
wink_sdk_extranet_property/models/custom_monetary_amount.py
wink_sdk_extranet_property/models/filter_descriptor_supplier.py
wink_sdk_extranet_property/models/general_manager_supplier.py
wink_sdk_extranet_property/models/generic_error_message.py
wink_sdk_extranet_property/models/geo_json_point_supplier.py
wink_sdk_extranet_property/models/geo_name_lightweight_supplier.py
wink_sdk_extranet_property-0.0.57.dist-info/licenses/LICENSE
wink_sdk_extranet_property-0.0.57.dist-info/METADATA
wink_sdk_extranet_property-0.0.57.dist-info/WHEEL
wink_sdk_extranet_property-0.0.57.dist-info/top_level.txt
wink_sdk_extranet_property-0.0.57.dist-info/RECORD
